{
	"questions": [
		{
			"text": "What will be the output of the following:<br>alert(new Array(4));",
			"answers": [
				",,,",
				",,,,",
				",,",
				"....",
				"...",
				"..",
				"null,null,null,null",
				"undefined,undefined, undefined,undefined"
			]
		},
		{
			"text": "What will be the output of the following:<br>alert(Number.MAX_VALUE + 100 - Number.MAX_VALUE);",
			"answers": [
				"0",
				"100",
				"-100",
				"Infinity",
				"Infinity + 100",
				"null",
				"undefined",
				"Overflow"
			]
		},
		{
			"text": "What will be the output of the following:<br>alert(Infinity - Infinity);",
			"answers": [
				"NaN",
				"undefined",
				"null",
				"0",
				"0.4681257e-308",
				"Infinity"
			]
		},
		{
			"text": "What will be the output of the following:<br>alert(true / 2 + false - 3);",
			"answers": [
				"-2.5",
				"2.5",
				"true",
				"false",
				"undefined",
				"null"
			]
		},
		{
			"text": "What will be the output of the following:<br>alert(!new Array(4)[3] || true==false);",
			"answers": [
				"true",
				"false",
				"undefined",
				"null",
				"0",
				"1"
			]
		},
		{
			"text": "What will be the output of the following:<br>alert(!!1==false==!!!true==-100+101);",
			"answers": [
				"true",
				"false",
				"1",
				"0",
				"null",
				"undefined"
			]
		},
		{
			"text": "What will be the output of the following:<br>var a, b;<br>alert(a + b);",
			"answers": [
				"NaN",
				"0",
				"undefined",
				"undefined undefined",
				"NaN undefined",
				"undefined NaN"
			]
		},
		{
			"text": "What will be the output of the following:<br>var a = 5, a = a - a + 5;<br>alert(a == (a = 6));",
			"answers": [
				"false",
				"true",
				"undefined",
				"null",
				"5",
				"6"
			]
		},
		{
			"text": "What will be the output of the following:<br>var a = 5;<br>alert((a == a + 1 - 1) * <br>(a == a - 1) + a);",
			"answers": [
				"5",
				"0",
				"true",
				"false",
				"undefined",
				"6",
				"-1",
				"80"
			]
		},
		{
			"text": "What will be the output of the following:<br>alert(typeof(Array));",
			"answers": [
				"function",
				"array",
				"constructor",
				"undefined",
				"infinity",
				"0",
				"1",
				"Object",
				"object"
			]
		},
		{
			"text": "What will be the output of the following:<br>alert(typeof(null));",
			"answers": [
				"object",
				"Object",
				"function",
				"array",
				"constructor",
				"undefined",
				"NaN",
				"0",
				"1"
			]
		},
		{
			"text": "What will be the output of the following:<br>alert(5 + 5 - '' + 5 + '');",
			"answers": [
				"15",
				"10",
				"5",
				"NaN",
				"undefined",
				"0"
			]
		},
		{
			"text": "What will be the output of the following:<br>alert((2,5 - 1) * 2);",
			"answers": [
				"6",
				"1",
				"3",
				"-3",
				"-6",
				"-1"
			]
		},
		{
			"text": "What is the extention of a JavaScript file?",
			"answers": [
				".js",
				".javas",
				".jscript",
				".jsp",
				".script",
				".java"
			]
		},
		{
			"text": "Is the following true or false?<br>JavaScript and Java are very similar programming languages",
			"answers": [
				"False",
				"True"			
			]
		},
		{
			"text": "Is the following true or false?<br>JavaScript is a trademark of Oracle Corporation",
			"answers": [
				"True",
				"False",
				"Only after 6 PM",
				"Only on Mondays"
			]
		},
		{
			"text": "Is the following true or false?<br>JavaScript is a weakly typed language",
			"answers": [
				"True",
				"False",
				"Only after the midnight",
				"Only when it's snowing",
				"We can decide it ourselves at runtime"
			]
		},
		{
			"text": "Is the following true or false?<br>JavaScript is used only for the client-side",
			"answers": [
				"False",
				"True"
			]
		},
		{
			"text": "Is the following true or false?<br>JavaScript is implemented in the same way in all the browsers",
			"answers": [
				"False",
				"True",
				"In Firefox and Chrome only",
				"In Safari and IE only"				
			]
		},
		{
			"text": "Is the following true or false?<br>JavaScript can remove the &lt;html&gt; tag<br>from the document page",
			"answers": [
				"True",
				"False",
				"Depends on the weather",
				"Depends on the web page type"				
			]
		}
	],
	"introText": "Sometimes Winter evenings are getting too cold and the warmth in our hearts starts to fade away... \n\n In times like these all that we need is a drop of light, the spring sun that will chase away the cold and blue feelings. \n\n This JavaScript quiz was made in the name of Spring. Every correct answer will give a bit of warm JavaScript energy to the dying flower of life that is our only hope for bringing Spring back...\n\nHurry up, with every xxxxxx seconds Winter steals 1 percent from the life energy. And we need at least 75% of energy..."
}
